grbl2image/__init__.py
grbl2image/grbl2image.py
grbl2image-1.2.2.dist-info/LICENSE
grbl2image-1.2.2.dist-info/METADATA
grbl2image-1.2.2.dist-info/WHEEL
grbl2image-1.2.2.dist-info/top_level.txt
grbl2image-1.2.2.dist-info/RECORD
