Metadata-Version: 2.1
Name: grbl2image
Version: 1.2.2
Summary: Generates an image (PNG, JPEG, etc.) from a GRBL file (.NC, .GC, ...) in Python using pillow (python3)
Author: AlanFromJapan
Project-URL: Homepage, https://github.com/AlanFromJapan/grbl2image
Project-URL: Bug Tracker, https://github.com/AlanFromJapan/grbl2image/issues
Project-URL: Parent project, https://github.com/AlanFromJapan/GrblWebStreamer
Classifier: Programming Language :: Python :: 3
Classifier: License :: OSI Approved :: MIT License
Classifier: Operating System :: OS Independent
Requires-Python: >=3.7
License-File: LICENSE
Requires-Dist: Pillow >=9.0
